xba2l/__init__.py
xba2l/__version__.py
xba2l/a2l_base.py
xba2l/a2l_lib.py
xba2l/a2l_util.py
xba2l/performance.py
xba2l/a2l/__init__.py
xba2l/a2l/a2l_core.py
xba2l/a2l/a2l_module.py
xba2l/a2l/a2l_reader.py
xba2l/etc/__init__.py
xba2l/etc/errors.py
xba2l/etc/i18n.py
xba2l/etc/options.py
xba2l/etc/reader.py
xba2l/etc/tool.py
xba2l-0.3.54.dist-info/LICENSE
xba2l-0.3.54.dist-info/METADATA
xba2l-0.3.54.dist-info/WHEEL
xba2l-0.3.54.dist-info/top_level.txt
xba2l-0.3.54.dist-info/RECORD
